emoji_bars/__init__.py
emoji_bars/bar.py
emoji_bars/emoji_surround.py
emoji_bars/loading_bar.py
emoji_bars-2.1.0.dist-info/METADATA
emoji_bars-2.1.0.dist-info/WHEEL
emoji_bars-2.1.0.dist-info/top_level.txt
emoji_bars-2.1.0.dist-info/RECORD
