Metadata-Version: 2.4
Name: emoji_bars
Version: 2.1.0
Summary: A Python module for creating emoji-based progress bars.
Author-email: Mathdallas <jaimorampudi164@gmail.com>
Project-URL: Homepage, https://github.com/Mathdallas-code/Emoji-Bars
Project-URL: Repository, https://github.com/Mathdallas-code/Emoji-Bars
Keywords: emoji,progress bar,visualization,terminal
Requires-Python: >=3.7
